Metadata-Version: 2.1
Name: gruut_lang_en
Version: 2.0.0
Summary: English language files for gruut tokenizer/phonemizer
Home-page: https://github.com/rhasspy/gruut
Author: Michael Hansen
Author-email: mike@rhasspy.org
License: UNKNOWN
Platform: UNKNOWN
Classifier: Programming Language :: Python :: 3
Classifier: License :: OSI Approved :: MIT License
